llm/__init__.py
llm/io.py
llm/llm.py
llm/prompt.py
data_science_llm_core-0.1.2.dist-info/METADATA
data_science_llm_core-0.1.2.dist-info/WHEEL
data_science_llm_core-0.1.2.dist-info/RECORD
