Metadata-Version: 2.1
Name: data-science-llm-core
Version: 0.1.2
Summary: 
Author: Unsal Gokdag
Author-email: unsal.gokdag@forto.com
Requires-Python: >=3.10,<3.11
Classifier: Programming Language :: Python :: 3
Classifier: Programming Language :: Python :: 3.10
Requires-Dist: backoff (>=2.2.1,<3.0.0)
Requires-Dist: openai (>=0.28.0,<0.29.0)
Requires-Dist: python-dotenv (>=0.20.0,<0.21.0)
